simpleDirectorySetup/__init__.py
simpleDirectorySetup/directoryConfig.py
simpleDirectorySetup-0.1.0.dist-info/METADATA
simpleDirectorySetup-0.1.0.dist-info/WHEEL
simpleDirectorySetup-0.1.0.dist-info/top_level.txt
simpleDirectorySetup-0.1.0.dist-info/RECORD
