Metadata-Version: 2.1
Name: simpleDirectorySetup
Version: 0.1.0
Summary: Pacote Facilitador Para Manipulação de Diretorios
Author: Marco Rocha
Author-email: <marco.rocha2@outlook.com>
Keywords: python,first package
Classifier: Development Status :: 3 - Alpha
Classifier: Intended Audience :: Education
Classifier: Programming Language :: Python :: 2
Classifier: Programming Language :: Python :: 3
Classifier: Operating System :: MacOS :: MacOS X
Classifier: Operating System :: Microsoft :: Windows
